lzl/__init__.py
lazyloads-1.0.1.dist-info/LICENSE
lazyloads-1.0.1.dist-info/METADATA
lazyloads-1.0.1.dist-info/WHEEL
lazyloads-1.0.1.dist-info/top_level.txt
lazyloads-1.0.1.dist-info/RECORD
