Metadata-Version: 2.1
Name: lazyloads
Version: 1.0.1
Summary: Python Module to make your life easier
Home-page: https://github.com/feimaomiao/lazyloads
Author: Matthew Lam
Author-email: lcpmatthew@gmail.com
License: UNKNOWN
Keywords: lazy built in function expansion extension other
Platform: UNKNOWN
Classifier: Programming Language :: Python :: 3
Classifier: Programming Language :: Python :: 3.6
Classifier: Programming Language :: Python :: 3.7
Classifier: Programming Language :: Python :: 3.8
Classifier: Natural Language :: English
Classifier: License :: OSI Approved :: MIT License
Classifier: Intended Audience :: Developers
Classifier: Operating System :: OS Independent
Classifier: Topic :: Software Development :: Libraries :: Python Modules
Requires-Python: >=3.6
